{
  "totalDuration": 10737.0,
  "segments": [
    {
      "start": 57.885,
      "duration": 3.166000000000004
    },
    {
      "start": 62.551,
      "duration": 4.125
    },
    {
      "start": 67.176,
      "duration": 27.834000000000003
    },
    {
      "start": 96.634,
      "duration": 4.959000000000003
    },
    {
      "start": 101.801,
      "duration": 14.125
    },
    {
      "start": 117.01,
      "duration": 5.498999999999995
    },
    {
      "start": 123.718,
      "duration": 14.49900000000001
    },
    {
      "start": 139.384,
      "duration": 3.0
    },
    {
      "start": 143.593,
      "duration": 4.0
    },
    {
      "start": 148.384,
      "duration": 11.0
    },
    {
      "start": 159.593,
      "duration": 10.417000000000002
    },
    {
      "start": 172.426,
      "duration": 2.875
    },
    {
      "start": 175.968,
      "duration": 3.0
    },
    {
      "start": 179.676,
      "duration": 3.0
    },
    {
      "start": 183.76,
      "duration": 6.832999999999998
    },
    {
      "start": 193.384,
      "duration": 4.167000000000002
    },
    {
      "start": 199.551,
      "duration": 4.417000000000002
    },
    {
      "start": 210.718,
      "duration": 5.624000000000024
    },
    {
      "start": 216.384,
      "duration": 2.584000000000003
    },
    {
      "start": 219.301,
      "duration": 8.417000000000002
    },
    {
      "start": 230.76,
      "duration": 7.498999999999995
    },
    {
      "start": 261.259,
      "duration": 28.584000000000003
    },
    {
      "start": 290.092,
      "duration": 38.459
    },
    {
      "start": 328.634,
      "duration": 4.58299999999997
    },
    {
      "start": 333.259,
      "duration": 8.375
    },
    {
      "start": 342.134,
      "duration": 8.459000000000003
    },
    {
      "start": 351.593,
      "duration": 12.33299999999997
    },
    {
      "start": 364.301,
      "duration": 9.875
    },
    {
      "start": 374.76,
      "duration": 4.790999999999997
    },
    {
      "start": 380.217,
      "duration": 16.584000000000003
    },
    {
      "start": 411.342,
      "duration": 2.084000000000003
    },
    {
      "start": 418.885,
      "duration": 3.0
    },
    {
      "start": 426.593,
      "duration": 17.33299999999997
    },
    {
      "start": 468.468,
      "duration": 6.95799999999997
    },
    {
      "start": 475.634,
      "duration": 3.959000000000003
    },
    {
      "start": 480.01,
      "duration": 2.290999999999997
    },
    {
      "start": 484.676,
      "duration": 6.5
    },
    {
      "start": 492.259,
      "duration": 3.125
    },
    {
      "start": 495.551,
      "duration": 5.29200000000003
    },
    {
      "start": 502.968,
      "duration": 2.95799999999997
    },
    {
      "start": 507.301,
      "duration": 5.625000000000057
    },
    {
      "start": 513.968,
      "duration": 2.79200000000003
    },
    {
      "start": 528.01,
      "duration": 5.499000000000024
    },
    {
      "start": 533.634,
      "duration": 2.2089999999999463
    },
    {
      "start": 545.301,
      "duration": 3.75
    },
    {
      "start": 556.509,
      "duration": 12.16700000000003
    },
    {
      "start": 569.968,
      "duration": 26.0
    },
    {
      "start": 596.384,
      "duration": 7.583999999999946
    },
    {
      "start": 604.176,
      "duration": 18.625
    },
    {
      "start": 623.01,
      "duration": 2.3319999999999936
    },
    {
      "start": 625.509,
      "duration": 2.16700000000003
    },
    {
      "start": 690.01,
      "duration": 3.0
    },
    {
      "start": 693.426,
      "duration": 2.4169999999999163
    },
    {
      "start": 702.885,
      "duration": 7.749000000000024
    },
    {
      "start": 725.176,
      "duration": 9.20799999999997
    },
    {
      "start": 737.468,
      "duration": 2.54200000000003
    },
    {
      "start": 741.051,
      "duration": 5.25
    },
    {
      "start": 767.259,
      "duration": 9.83299999999997
    },
    {
      "start": 778.342,
      "duration": 33.70900000000006
    },
    {
      "start": 1052.426,
      "duration": 24.042000000000144
    },
    {
      "start": 1097.926,
      "duration": 4.83400000000006
    },
    {
      "start": 1112.426,
      "duration": 11.33400000000006
    },
    {
      "start": 1124.676,
      "duration": 4.917000000000144
    },
    {
      "start": 1130.426,
      "duration": 4.833000000000084
    },
    {
      "start": 1135.509,
      "duration": 3.33400000000006
    },
    {
      "start": 1139.01,
      "duration": 5.583000000000084
    },
    {
      "start": 1145.051,
      "duration": 4.83400000000006
    },
    {
      "start": 1168.176,
      "duration": 2.25
    },
    {
      "start": 1171.301,
      "duration": 2.0410000000001673
    },
    {
      "start": 1173.593,
      "duration": 2.66599999999994
    },
    {
      "start": 1176.468,
      "duration": 4.04099999999994
    },
    {
      "start": 1180.593,
      "duration": 4.166999999999916
    },
    {
      "start": 1185.551,
      "duration": 2.875
    },
    {
      "start": 1188.76,
      "duration": 6.708000000000084
    },
    {
      "start": 1195.509,
      "duration": 17.75
    },
    {
      "start": 1215.468,
      "duration": 11.375
    },
    {
      "start": 1227.76,
      "duration": 8.083000000000084
    },
    {
      "start": 1236.301,
      "duration": 3.45900000000006
    },
    {
      "start": 1240.092,
      "duration": 6.291999999999916
    },
    {
      "start": 1252.718,
      "duration": 4.082999999999856
    },
    {
      "start": 1262.301,
      "duration": 4.0
    },
    {
      "start": 1300.051,
      "duration": 4.375
    },
    {
      "start": 1304.801,
      "duration": 4.917000000000144
    },
    {
      "start": 1311.134,
      "duration": 9.083000000000084
    },
    {
      "start": 1320.676,
      "duration": 2.25
    },
    {
      "start": 1323.051,
      "duration": 3.875
    },
    {
      "start": 1329.134,
      "duration": 4.083000000000084
    },
    {
      "start": 1333.259,
      "duration": 4.20900000000006
    },
    {
      "start": 1345.342,
      "duration": 3.0419999999999163
    },
    {
      "start": 1350.76,
      "duration": 3.25
    },
    {
      "start": 1359.551,
      "duration": 2.5830000000000837
    },
    {
      "start": 1362.718,
      "duration": 10.624000000000024
    },
    {
      "start": 1373.926,
      "duration": 2.2910000000001673
    },
    {
      "start": 1376.801,
      "duration": 8.0
    },
    {
      "start": 1388.384,
      "duration": 5.708000000000084
    },
    {
      "start": 1396.801,
      "duration": 2.3330000000000837
    },
    {
      "start": 1400.718,
      "duration": 4.66599999999994
    },
    {
      "start": 1535.76,
      "duration": 6.582000000000107
    },
    {
      "start": 1545.426,
      "duration": 3.7080000000000837
    },
    {
      "start": 1549.676,
      "duration": 5.042000000000144
    },
    {
      "start": 1556.509,
      "duration": 3.1669999999999163
    },
    {
      "start": 1560.01,
      "duration": 4.249000000000024
    },
    {
      "start": 1564.301,
      "duration": 7.791000000000167
    },
    {
      "start": 1572.926,
      "duration": 9.166000000000167
    },
    {
      "start": 1592.76,
      "duration": 2.79099999999994
    },
    {
      "start": 1595.593,
      "duration": 8.54099999999994
    },
    {
      "start": 1605.593,
      "duration": 4.125
    },
    {
      "start": 1610.051,
      "duration": 12.083000000000084
    },
    {
      "start": 1632.426,
      "duration": 5.58400000000006
    },
    {
      "start": 1639.426,
      "duration": 4.625
    },
    {
      "start": 1646.217,
      "duration": 7.333999999999833
    },
    {
      "start": 1664.468,
      "duration": 5.749000000000024
    },
    {
      "start": 1670.426,
      "duration": 3.7080000000000837
    },
    {
      "start": 1678.176,
      "duration": 3.0830000000000837
    },
    {
      "start": 1684.051,
      "duration": 5.458000000000084
    },
    {
      "start": 1690.718,
      "duration": 3.0419999999999163
    },
    {
      "start": 1694.051,
      "duration": 3.875
    },
    {
      "start": 1700.01,
      "duration": 8.0
    },
    {
      "start": 1708.468,
      "duration": 5.291999999999916
    },
    {
      "start": 1719.509,
      "duration": 3.3759999999999764
    },
    {
      "start": 1723.509,
      "duration": 3.1669999999999163
    },
    {
      "start": 1727.342,
      "duration": 5.708999999999833
    },
    {
      "start": 1734.468,
      "duration": 6.04099999999994
    },
    {
      "start": 1741.885,
      "duration": 5.16599999999994
    },
    {
      "start": 1755.593,
      "duration": 5.082999999999856
    },
    {
      "start": 1762.134,
      "duration": 18.041999999999916
    },
    {
      "start": 1781.301,
      "duration": 6.875
    },
    {
      "start": 1789.259,
      "duration": 9.541999999999916
    },
    {
      "start": 1799.176,
      "duration": 5.166000000000167
    },
    {
      "start": 1806.509,
      "duration": 4.041999999999916
    },
    {
      "start": 1844.885,
      "duration": 4.125
    },
    {
      "start": 1882.801,
      "duration": 4.416000000000167
    },
    {
      "start": 1887.843,
      "duration": 12.0
    },
    {
      "start": 1900.676,
      "duration": 14.833000000000084
    },
    {
      "start": 1921.551,
      "duration": 16.45900000000006
    },
    {
      "start": 1938.384,
      "duration": 3.45900000000006
    },
    {
      "start": 1948.01,
      "duration": 7.0
    },
    {
      "start": 1955.342,
      "duration": 14.417999999999893
    },
    {
      "start": 1973.843,
      "duration": 10.66599999999994
    },
    {
      "start": 1984.801,
      "duration": 6.708000000000084
    },
    {
      "start": 1991.676,
      "duration": 2.5
    },
    {
      "start": 1996.01,
      "duration": 6.54099999999994
    },
    {
      "start": 2004.634,
      "duration": 10.708000000000084
    },
    {
      "start": 2024.342,
      "duration": 6.833999999999833
    },
    {
      "start": 2031.342,
      "duration": 10.875
    },
    {
      "start": 2042.968,
      "duration": 4.54099999999994
    },
    {
      "start": 2047.7179999999998,
      "duration": 6.458000000000084
    },
    {
      "start": 2054.468,
      "duration": 15.583000000000084
    },
    {
      "start": 2070.384,
      "duration": 6.458999999999833
    },
    {
      "start": 2077.134,
      "duration": 3.5419999999999163
    },
    {
      "start": 2080.885,
      "duration": 3.4989999999997963
    },
    {
      "start": 2085.176,
      "duration": 2.875
    },
    {
      "start": 2089.01,
      "duration": 2.832999999999629
    },
    {
      "start": 2128.885,
      "duration": 1.875
    },
    {
      "start": 2131.176,
      "duration": 2.0
    },
    {
      "start": 2134.134,
      "duration": 2.4589999999998327
    },
    {
      "start": 2157.551,
      "duration": 5.125
    },
    {
      "start": 2193.885,
      "duration": 4.0
    },
    {
      "start": 2200.718,
      "duration": 3.4580000000000837
    },
    {
      "start": 2219.051,
      "duration": 17.959000000000287
    },
    {
      "start": 2241.509,
      "duration": 7.541999999999916
    },
    {
      "start": 2252.176,
      "duration": 9.0
    },
    {
      "start": 2263.551,
      "duration": 6.791000000000167
    },
    {
      "start": 2274.676,
      "duration": 2.5
    },
    {
      "start": 2278.885,
      "duration": 7.0
    },
    {
      "start": 2286.217,
      "duration": 2.66800000000012
    },
    {
      "start": 2291.01,
      "duration": 2.582999999999629
    },
    {
      "start": 2295.968,
      "duration": 3.042000000000371
    },
    {
      "start": 2301.509,
      "duration": 3.0
    },
    {
      "start": 2318.134,
      "duration": 2.5419999999999163
    },
    {
      "start": 2331.092,
      "duration": 2.750999999999749
    },
    {
      "start": 2335.801,
      "duration": 2.7919999999999163
    },
    {
      "start": 2338.634,
      "duration": 3.2089999999998327
    },
    {
      "start": 2347.634,
      "duration": 4.541999999999916
    },
    {
      "start": 2352.551,
      "duration": 7.125
    },
    {
      "start": 2363.051,
      "duration": 5.0
    },
    {
      "start": 2371.634,
      "duration": 5.291999999999916
    },
    {
      "start": 2377.01,
      "duration": 7.665999999999713
    },
    {
      "start": 2386.676,
      "duration": 3.7080000000000837
    },
    {
      "start": 2392.176,
      "duration": 3.0
    },
    {
      "start": 2411.01,
      "duration": 4.498999999999796
    },
    {
      "start": 2556.843,
      "duration": 14.083000000000084
    },
    {
      "start": 2571.718,
      "duration": 19.708000000000084
    },
    {
      "start": 2595.468,
      "duration": 31.458000000000084
    },
    {
      "start": 2627.634,
      "duration": 3.3760000000002037
    },
    {
      "start": 2631.176,
      "duration": 42.458000000000084
    },
    {
      "start": 2673.676,
      "duration": 9.25
    },
    {
      "start": 2687.843,
      "duration": 18.583000000000084
    },
    {
      "start": 2706.509,
      "duration": 6.501000000000204
    },
    {
      "start": 2716.885,
      "duration": 9.875
    },
    {
      "start": 2729.509,
      "duration": 2.2510000000002037
    },
    {
      "start": 2735.217,
      "duration": 3.125
    },
    {
      "start": 2748.342,
      "duration": 3.8339999999998327
    },
    {
      "start": 2754.342,
      "duration": 3.66800000000012
    },
    {
      "start": 2759.634,
      "duration": 13.376000000000204
    },
    {
      "start": 2773.509,
      "duration": 2.875
    },
    {
      "start": 2777.801,
      "duration": 6.209000000000287
    },
    {
      "start": 2785.217,
      "duration": 7.333999999999833
    },
    {
      "start": 2793.634,
      "duration": 6.791999999999916
    },
    {
      "start": 2801.134,
      "duration": 8.458999999999833
    },
    {
      "start": 2809.676,
      "duration": 9.416000000000167
    },
    {
      "start": 2845.176,
      "duration": 2.8340000000002874
    },
    {
      "start": 2868.426,
      "duration": 2.0
    },
    {
      "start": 2871.01,
      "duration": 14.248999999999796
    },
    {
      "start": 2981.801,
      "duration": 3.2090000000002874
    },
    {
      "start": 2985.676,
      "duration": 2.8330000000000837
    },
    {
      "start": 2990.509,
      "duration": 2.2089999999998327
    },
    {
      "start": 2996.718,
      "duration": 2.9580000000000837
    },
    {
      "start": 3000.342,
      "duration": 7.875
    },
    {
      "start": 3009.134,
      "duration": 10.291999999999916
    },
    {
      "start": 3019.634,
      "duration": 11.708000000000084
    },
    {
      "start": 3032.968,
      "duration": 2.7080000000000837
    },
    {
      "start": 3035.801,
      "duration": 4.875
    },
    {
      "start": 3040.968,
      "duration": 2.5410000000001673
    },
    {
      "start": 3045.01,
      "duration": 6.875
    },
    {
      "start": 3052.01,
      "duration": 2.6659999999997126
    },
    {
      "start": 3055.718,
      "duration": 18.541000000000167
    },
    {
      "start": 3074.509,
      "duration": 3.2089999999998327
    },
    {
      "start": 3078.384,
      "duration": 11.626000000000204
    },
    {
      "start": 3126.509,
      "duration": 2.8330000000000837
    },
    {
      "start": 3163.634,
      "duration": 2.0
    },
    {
      "start": 3167.176,
      "duration": 3.8340000000002874
    },
    {
      "start": 3172.676,
      "duration": 2.7080000000000837
    },
    {
      "start": 3184.509,
      "duration": 5.166999999999916
    },
    {
      "start": 3190.01,
      "duration": 6.0
    },
    {
      "start": 3272.676,
      "duration": 5.0
    },
    {
      "start": 3282.843,
      "duration": 3.917000000000371
    },
    {
      "start": 3288.301,
      "duration": 18.709000000000287
    },
    {
      "start": 3311.217,
      "duration": 3.79300000000012
    },
    {
      "start": 3315.051,
      "duration": 24.959000000000287
    },
    {
      "start": 3357.134,
      "duration": 2.8760000000002037
    },
    {
      "start": 3364.134,
      "duration": 2.375
    },
    {
      "start": 3388.259,
      "duration": 4.0
    },
    {
      "start": 3399.134,
      "duration": 6.583999999999833
    },
    {
      "start": 3405.885,
      "duration": 3.7909999999997126
    },
    {
      "start": 3410.843,
      "duration": 4.333000000000084
    },
    {
      "start": 3417.968,
      "duration": 8.208000000000084
    },
    {
      "start": 3448.384,
      "duration": 25.501000000000204
    },
    {
      "start": 3474.134,
      "duration": 11.041999999999916
    },
    {
      "start": 3485.968,
      "duration": 4.75
    },
    {
      "start": 3491.843,
      "duration": 2.917000000000371
    },
    {
      "start": 3495.384,
      "duration": 12.125
    },
    {
      "start": 3508.051,
      "duration": 4.666999999999916
    },
    {
      "start": 3514.342,
      "duration": 2.54300000000012
    },
    {
      "start": 3517.051,
      "duration": 3.4580000000000837
    },
    {
      "start": 3524.468,
      "duration": 17.958000000000084
    },
    {
      "start": 3549.176,
      "duration": 3.875
    },
    {
      "start": 3577.217,
      "duration": 4.958999999999833
    },
    {
      "start": 3583.926,
      "duration": 2.8340000000002874
    },
    {
      "start": 3607.384,
      "duration": 2.875
    },
    {
      "start": 3614.468,
      "duration": 8.542000000000371
    },
    {
      "start": 3623.342,
      "duration": 4.833999999999833
    },
    {
      "start": 3628.718,
      "duration": 10.791000000000167
    },
    {
      "start": 3639.801,
      "duration": 2.625
    },
    {
      "start": 3657.509,
      "duration": 2.1669999999999163
    },
    {
      "start": 3660.051,
      "duration": 5.333000000000084
    },
    {
      "start": 3668.217,
      "duration": 3.125
    },
    {
      "start": 3671.509,
      "duration": 2.6669999999999163
    },
    {
      "start": 3680.676,
      "duration": 7.5
    },
    {
      "start": 3688.885,
      "duration": 3.832999999999629
    },
    {
      "start": 3694.134,
      "duration": 5.083000000000084
    },
    {
      "start": 3700.301,
      "duration": 3.75
    },
    {
      "start": 3714.176,
      "duration": 3.9160000000001673
    },
    {
      "start": 3722.301,
      "duration": 2.125
    },
    {
      "start": 3725.342,
      "duration": 2.375999999999749
    },
    {
      "start": 3732.384,
      "duration": 3.1669999999999163
    },
    {
      "start": 3736.176,
      "duration": 2.75
    },
    {
      "start": 3739.885,
      "duration": 2.6239999999997963
    },
    {
      "start": 3751.509,
      "duration": 2.2919999999999163
    },
    {
      "start": 3783.843,
      "duration": 6.75
    },
    {
      "start": 3790.801,
      "duration": 6.041999999999916
    },
    {
      "start": 3806.301,
      "duration": 3.9160000000001673
    },
    {
      "start": 3826.718,
      "duration": 4.791000000000167
    },
    {
      "start": 3888.342,
      "duration": 16.0
    },
    {
      "start": 3904.843,
      "duration": 9.374000000000251
    },
    {
      "start": 3917.301,
      "duration": 8.375
    },
    {
      "start": 3926.384,
      "duration": 5.958000000000084
    },
    {
      "start": 3934.509,
      "duration": 5.833000000000084
    },
    {
      "start": 3940.76,
      "duration": 5.165999999999713
    },
    {
      "start": 3964.509,
      "duration": 4.833000000000084
    },
    {
      "start": 3969.551,
      "duration": 2.9169999999999163
    },
    {
      "start": 3974.509,
      "duration": 16.416999999999916
    },
    {
      "start": 3991.301,
      "duration": 3.5840000000002874
    },
    {
      "start": 3996.134,
      "duration": 7.626000000000204
    },
    {
      "start": 4020.176,
      "duration": 4.916000000000167
    },
    {
      "start": 4026.217,
      "duration": 5.833999999999833
    },
    {
      "start": 4032.217,
      "duration": 11.250999999999749
    },
    {
      "start": 4050.01,
      "duration": 4.540999999999713
    },
    {
      "start": 4071.384,
      "duration": 2.4169999999999163
    },
    {
      "start": 4074.384,
      "duration": 2.4589999999998327
    },
    {
      "start": 4084.801,
      "duration": 3.75
    },
    {
      "start": 4089.01,
      "duration": 4.498999999999796
    },
    {
      "start": 4093.676,
      "duration": 4.334000000000287
    },
    {
      "start": 4098.843,
      "duration": 2.4989999999997963
    },
    {
      "start": 4102.301,
      "duration": 4.416999999999462
    },
    {
      "start": 4107.843,
      "duration": 3.3330000000005384
    },
    {
      "start": 4111.634,
      "duration": 3.292000000000371
    },
    {
      "start": 4115.634,
      "duration": 5.417000000000371
    },
    {
      "start": 4122.885,
      "duration": 4.832999999999629
    },
    {
      "start": 4131.301,
      "duration": 6.915999999999258
    },
    {
      "start": 4139.509,
      "duration": 6.417000000000371
    },
    {
      "start": 4146.217,
      "duration": 3.6260000000002037
    },
    {
      "start": 4195.551,
      "duration": 2.2089999999998327
    },
    {
      "start": 4200.342,
      "duration": 13.126000000000204
    },
    {
      "start": 4214.509,
      "duration": 10.167000000000371
    },
    {
      "start": 4240.718,
      "duration": 4.958000000000538
    },
    {
      "start": 4246.843,
      "duration": 7.458000000000538
    },
    {
      "start": 4254.801,
      "duration": 10.625
    },
    {
      "start": 4265.843,
      "duration": 18.16700000000037
    },
    {
      "start": 4285.634,
      "duration": 2.917000000000371
    },
    {
      "start": 4288.843,
      "duration": 7.875
    },
    {
      "start": 4299.01,
      "duration": 3.9160000000001673
    },
    {
      "start": 4303.217,
      "duration": 5.167000000000371
    },
    {
      "start": 4309.634,
      "duration": 6.083999999999833
    },
    {
      "start": 4316.051,
      "duration": 6.375
    },
    {
      "start": 4323.01,
      "duration": 12.166000000000167
    },
    {
      "start": 4335.301,
      "duration": 13.541999999999462
    },
    {
      "start": 4351.301,
      "duration": 27.875
    },
    {
      "start": 4382.676,
      "duration": 7.5
    },
    {
      "start": 4390.634,
      "duration": 6.707999999999629
    },
    {
      "start": 4398.885,
      "duration": 2.4989999999997963
    },
    {
      "start": 4402.342,
      "duration": 16.376000000000204
    },
    {
      "start": 4421.968,
      "duration": 2.875
    },
    {
      "start": 4425.259,
      "duration": 4.125
    },
    {
      "start": 4429.718,
      "duration": 8.0
    },
    {
      "start": 4437.801,
      "duration": 3.375
    },
    {
      "start": 4442.01,
      "duration": 6.0
    },
    {
      "start": 4451.217,
      "duration": 15.668000000000575
    },
    {
      "start": 4476.217,
      "duration": 2.334000000000742
    },
    {
      "start": 4479.176,
      "duration": 3.165999999999258
    },
    {
      "start": 4484.968,
      "duration": 6.042000000000371
    },
    {
      "start": 4493.551,
      "duration": 2.4589999999998327
    },
    {
      "start": 4496.843,
      "duration": 5.498999999999796
    },
    {
      "start": 4519.801,
      "duration": 6.707999999999629
    },
    {
      "start": 4527.051,
      "duration": 10.207999999999629
    },
    {
      "start": 4538.051,
      "duration": 4.541999999999462
    },
    {
      "start": 4544.217,
      "duration": 3.834000000000742
    },
    {
      "start": 4568.384,
      "duration": 8.792000000000371
    },
    {
      "start": 4577.509,
      "duration": 3.042000000000371
    },
    {
      "start": 4580.885,
      "duration": 5.082999999999629
    },
    {
      "start": 4586.051,
      "duration": 4.125
    },
    {
      "start": 4591.01,
      "duration": 6.248999999999796
    },
    {
      "start": 4598.176,
      "duration": 7.25
    },
    {
      "start": 4608.885,
      "duration": 13.623999999999796
    },
    {
      "start": 4622.676,
      "duration": 4.582999999999629
    },
    {
      "start": 4628.134,
      "duration": 5.458999999999833
    },
    {
      "start": 4660.885,
      "duration": 2.832999999999629
    },
    {
      "start": 4681.342,
      "duration": 8.875
    },
    {
      "start": 4690.885,
      "duration": 7.748999999999796
    },
    {
      "start": 4698.676,
      "duration": 5.665999999999258
    },
    {
      "start": 4715.551,
      "duration": 3.875
    },
    {
      "start": 4723.843,
      "duration": 7.416000000000167
    },
    {
      "start": 4731.718,
      "duration": 3.7910000000001673
    },
    {
      "start": 4752.843,
      "duration": 4.248999999999796
    },
    {
      "start": 4757.176,
      "duration": 18.915999999999258
    },
    {
      "start": 4781.676,
      "duration": 9.5
    },
    {
      "start": 4792.217,
      "duration": 18.501000000000204
    },
    {
      "start": 4813.051,
      "duration": 12.958999999999833
    },
    {
      "start": 4826.676,
      "duration": 8.166999999999462
    },
    {
      "start": 4859.342,
      "duration": 3.543000000000575
    },
    {
      "start": 4872.176,
      "duration": 6.416999999999462
    },
    {
      "start": 4878.801,
      "duration": 9.457999999999629
    },
    {
      "start": 4907.384,
      "duration": 2.4589999999998327
    },
    {
      "start": 4958.843,
      "duration": 2.917000000000371
    },
    {
      "start": 4961.968,
      "duration": 2.2910000000001673
    },
    {
      "start": 4966.176,
      "duration": 5.416999999999462
    },
    {
      "start": 4974.509,
      "duration": 5.542000000000371
    },
    {
      "start": 4980.634,
      "duration": 15.75
    },
    {
      "start": 4998.301,
      "duration": 9.75
    },
    {
      "start": 5008.468,
      "duration": 11.791000000000167
    },
    {
      "start": 5020.676,
      "duration": 2.582999999999629
    },
    {
      "start": 5024.384,
      "duration": 2.5010000000002037
    },
    {
      "start": 5029.176,
      "duration": 2.75
    },
    {
      "start": 5033.01,
      "duration": 4.166000000000167
    },
    {
      "start": 5038.051,
      "duration": 13.457999999999629
    },
    {
      "start": 5052.634,
      "duration": 13.582999999999629
    },
    {
      "start": 5080.926,
      "duration": 3.875
    },
    {
      "start": 5108.968,
      "duration": 7.708000000000538
    },
    {
      "start": 5136.468,
      "duration": 10.623999999999796
    },
    {
      "start": 5147.509,
      "duration": 6.0
    },
    {
      "start": 5169.051,
      "duration": 9.332999999999629
    },
    {
      "start": 5184.676,
      "duration": 5.540999999999258
    },
    {
      "start": 5210.301,
      "duration": 12.375
    },
    {
      "start": 5223.384,
      "duration": 2.4589999999998327
    },
    {
      "start": 5248.176,
      "duration": 12.5
    },
    {
      "start": 5265.843,
      "duration": 4.333000000000538
    },
    {
      "start": 5271.176,
      "duration": 2.5419999999994616
    },
    {
      "start": 5278.885,
      "duration": 5.456999999999425
    },
    {
      "start": 5295.801,
      "duration": 3.290999999999258
    },
    {
      "start": 5303.051,
      "duration": 3.165999999999258
    },
    {
      "start": 5307.926,
      "duration": 5.165999999999258
    },
    {
      "start": 5313.342,
      "duration": 3.334000000000742
    },
    {
      "start": 5318.217,
      "duration": 6.292000000000371
    },
    {
      "start": 5327.509,
      "duration": 5.417000000000371
    },
    {
      "start": 5373.843,
      "duration": 5.666000000000167
    },
    {
      "start": 5384.509,
      "duration": 5.042000000000371
    },
    {
      "start": 5430.551,
      "duration": 4.625
    },
    {
      "start": 5435.718,
      "duration": 3.3330000000005384
    },
    {
      "start": 5439.384,
      "duration": 2.957999999999629
    },
    {
      "start": 5444.217,
      "duration": 5.125
    },
    {
      "start": 5452.176,
      "duration": 5.5
    },
    {
      "start": 5459.01,
      "duration": 11.541000000000167
    },
    {
      "start": 5474.634,
      "duration": 21.70799999999963
    },
    {
      "start": 5497.176,
      "duration": 2.375
    },
    {
      "start": 5500.051,
      "duration": 2.5419999999994616
    },
    {
      "start": 5506.01,
      "duration": 4.498999999999796
    },
    {
      "start": 5512.01,
      "duration": 21.081999999999425
    },
    {
      "start": 5533.843,
      "duration": 2.917000000000371
    },
    {
      "start": 5537.509,
      "duration": 11.042000000000371
    },
    {
      "start": 5551.217,
      "duration": 3.292000000000371
    },
    {
      "start": 5556.551,
      "duration": 2.5
    },
    {
      "start": 5559.176,
      "duration": 8.416999999999462
    },
    {
      "start": 5567.676,
      "duration": 5.832999999999629
    },
    {
      "start": 5574.01,
      "duration": 7.582999999999629
    },
    {
      "start": 5582.051,
      "duration": 7.541999999999462
    },
    {
      "start": 5592.676,
      "duration": 3.5
    },
    {
      "start": 5596.301,
      "duration": 5.375
    },
    {
      "start": 5602.718,
      "duration": 6.208000000000538
    },
    {
      "start": 5609.718,
      "duration": 9.167000000000371
    },
    {
      "start": 5619.468,
      "duration": 4.708000000000538
    },
    {
      "start": 5627.051,
      "duration": 2.457999999999629
    },
    {
      "start": 5632.634,
      "duration": 7.208999999999833
    },
    {
      "start": 5640.176,
      "duration": 5.541999999999462
    },
    {
      "start": 5646.342,
      "duration": 6.167000000000371
    },
    {
      "start": 5653.634,
      "duration": 4.083999999999833
    },
    {
      "start": 5658.468,
      "duration": 3.542000000000371
    },
    {
      "start": 5737.384,
      "duration": 4.957999999999629
    },
    {
      "start": 5745.676,
      "duration": 13.415999999999258
    },
    {
      "start": 5759.676,
      "duration": 6.5
    },
    {
      "start": 5773.217,
      "duration": 6.543000000000575
    },
    {
      "start": 5781.01,
      "duration": 5.373999999999796
    },
    {
      "start": 5787.342,
      "duration": 5.834000000000742
    },
    {
      "start": 5793.718,
      "duration": 6.791000000000167
    },
    {
      "start": 5801.384,
      "duration": 2.667000000000371
    },
    {
      "start": 5805.885,
      "duration": 5.082999999999629
    },
    {
      "start": 5813.593,
      "duration": 14.0
    },
    {
      "start": 5830.259,
      "duration": 2.7089999999998327
    },
    {
      "start": 5833.509,
      "duration": 9.376000000000204
    },
    {
      "start": 5845.301,
      "duration": 3.125
    },
    {
      "start": 5851.676,
      "duration": 20.58299999999963
    },
    {
      "start": 5881.217,
      "duration": 6.0
    },
    {
      "start": 5887.676,
      "duration": 6.166999999999462
    },
    {
      "start": 5894.01,
      "duration": 16.916000000000167
    },
    {
      "start": 5914.926,
      "duration": 4.125
    },
    {
      "start": 5919.217,
      "duration": 2.6260000000002037
    },
    {
      "start": 5922.593,
      "duration": 8.417000000000371
    },
    {
      "start": 6025.134,
      "duration": 4.957999999999629
    },
    {
      "start": 6030.384,
      "duration": 2.542000000000371
    },
    {
      "start": 6047.843,
      "duration": 2.5830000000005384
    },
    {
      "start": 6053.843,
      "duration": 20.541000000000167
    },
    {
      "start": 6074.634,
      "duration": 3.707999999999629
    },
    {
      "start": 6079.509,
      "duration": 2.667000000000371
    },
    {
      "start": 6083.217,
      "duration": 2.668000000000575
    },
    {
      "start": 6088.509,
      "duration": 2.667000000000371
    },
    {
      "start": 6117.676,
      "duration": 3.582999999999629
    },
    {
      "start": 6122.01,
      "duration": 2.4989999999997963
    },
    {
      "start": 6125.301,
      "duration": 5.875
    },
    {
      "start": 6134.551,
      "duration": 2.375
    },
    {
      "start": 6184.509,
      "duration": 4.251000000000204
    },
    {
      "start": 6221.176,
      "duration": 4.416999999999462
    },
    {
      "start": 6226.468,
      "duration": 6.25
    },
    {
      "start": 6234.051,
      "duration": 11.125
    },
    {
      "start": 6249.468,
      "duration": 2.9160000000001673
    },
    {
      "start": 6254.176,
      "duration": 3.5839999999998327
    },
    {
      "start": 6261.468,
      "duration": 3.2080000000005384
    },
    {
      "start": 6265.968,
      "duration": 7.75
    },
    {
      "start": 6274.301,
      "duration": 3.5419999999994616
    },
    {
      "start": 6281.301,
      "duration": 7.875
    },
    {
      "start": 6291.468,
      "duration": 5.542000000000371
    },
    {
      "start": 6297.885,
      "duration": 5.957999999999629
    },
    {
      "start": 6310.051,
      "duration": 5.708999999999833
    },
    {
      "start": 6316.509,
      "duration": 5.707999999999629
    },
    {
      "start": 6323.468,
      "duration": 5.041000000000167
    },
    {
      "start": 6329.051,
      "duration": 3.375
    },
    {
      "start": 6338.885,
      "duration": 3.0
    },
    {
      "start": 6341.968,
      "duration": 2.5830000000005384
    },
    {
      "start": 6345.843,
      "duration": 3.8330000000005384
    },
    {
      "start": 6350.551,
      "duration": 3.540999999999258
    },
    {
      "start": 6354.634,
      "duration": 5.542000000000371
    },
    {
      "start": 6360.676,
      "duration": 2.582999999999629
    },
    {
      "start": 6403.509,
      "duration": 9.875
    },
    {
      "start": 6416.676,
      "duration": 16.25
    },
    {
      "start": 6434.051,
      "duration": 6.958999999999833
    },
    {
      "start": 6445.718,
      "duration": 2.8330000000005384
    },
    {
      "start": 6451.801,
      "duration": 2.875
    },
    {
      "start": 6456.551,
      "duration": 6.625
    },
    {
      "start": 6469.134,
      "duration": 3.207999999999629
    },
    {
      "start": 6473.342,
      "duration": 3.334000000000742
    },
    {
      "start": 6476.801,
      "duration": 2.75
    },
    {
      "start": 6485.301,
      "duration": 2.875
    },
    {
      "start": 6492.051,
      "duration": 2.7919999999994616
    },
    {
      "start": 6499.342,
      "duration": 3.292000000000371
    },
    {
      "start": 6502.968,
      "duration": 3.5410000000001673
    },
    {
      "start": 6507.134,
      "duration": 3.542000000000371
    },
    {
      "start": 6515.801,
      "duration": 2.290999999999258
    },
    {
      "start": 6539.01,
      "duration": 10.331999999999425
    },
    {
      "start": 6549.509,
      "duration": 6.376000000000204
    },
    {
      "start": 6568.551,
      "duration": 2.540999999999258
    },
    {
      "start": 6572.301,
      "duration": 2.2919999999994616
    },
    {
      "start": 6590.01,
      "duration": 2.2489999999997963
    },
    {
      "start": 6636.801,
      "duration": 2.832999999999629
    },
    {
      "start": 6639.676,
      "duration": 4.333999999999833
    },
    {
      "start": 6645.176,
      "duration": 5.0
    },
    {
      "start": 6650.801,
      "duration": 6.832999999999629
    },
    {
      "start": 6658.051,
      "duration": 6.958999999999833
    },
    {
      "start": 6665.509,
      "duration": 3.2510000000002037
    },
    {
      "start": 6669.551,
      "duration": 7.375
    },
    {
      "start": 6677.301,
      "duration": 3.332999999999629
    },
    {
      "start": 6680.801,
      "duration": 8.083999999999833
    },
    {
      "start": 6688.926,
      "duration": 14.125
    },
    {
      "start": 6704.968,
      "duration": 2.1239999999997963
    },
    {
      "start": 6707.509,
      "duration": 5.458999999999833
    },
    {
      "start": 6720.593,
      "duration": 2.3330000000005384
    },
    {
      "start": 6747.342,
      "duration": 11.75
    },
    {
      "start": 6760.134,
      "duration": 10.626000000000204
    },
    {
      "start": 6771.134,
      "duration": 4.542000000000371
    },
    {
      "start": 6775.718,
      "duration": 5.708000000000538
    },
    {
      "start": 6782.01,
      "duration": 4.457999999999629
    },
    {
      "start": 6789.051,
      "duration": 8.791999999999462
    },
    {
      "start": 6799.051,
      "duration": 3.7919999999994616
    },
    {
      "start": 6812.01,
      "duration": 4.166000000000167
    },
    {
      "start": 6834.01,
      "duration": 14.166000000000167
    },
    {
      "start": 6852.301,
      "duration": 4.125
    },
    {
      "start": 6856.551,
      "duration": 2.2919999999994616
    },
    {
      "start": 6889.342,
      "duration": 3.5010000000002037
    },
    {
      "start": 6897.217,
      "duration": 5.875
    },
    {
      "start": 6903.176,
      "duration": 2.040999999999258
    },
    {
      "start": 6910.468,
      "duration": 2.7910000000001673
    },
    {
      "start": 6914.342,
      "duration": 4.543000000000575
    },
    {
      "start": 6919.468,
      "duration": 4.708000000000538
    },
    {
      "start": 6957.509,
      "duration": 2.417000000000371
    },
    {
      "start": 6960.176,
      "duration": 7.416999999999462
    },
    {
      "start": 6968.676,
      "duration": 3.0
    },
    {
      "start": 6971.843,
      "duration": 12.167000000000371
    },
    {
      "start": 6987.051,
      "duration": 3.0
    },
    {
      "start": 6992.176,
      "duration": 5.5
    },
    {
      "start": 6997.843,
      "duration": 2.4160000000001673
    },
    {
      "start": 7001.301,
      "duration": 4.040999999999258
    },
    {
      "start": 7005.676,
      "duration": 6.083999999999833
    },
    {
      "start": 7012.134,
      "duration": 4.25
    },
    {
      "start": 7016.676,
      "duration": 4.582999999999629
    },
    {
      "start": 7021.468,
      "duration": 8.041000000000167
    },
    {
      "start": 7031.01,
      "duration": 13.666000000000167
    },
    {
      "start": 7048.676,
      "duration": 10.665999999999258
    },
    {
      "start": 7067.843,
      "duration": 4.0
    },
    {
      "start": 7075.676,
      "duration": 2.2919999999994616
    },
    {
      "start": 7078.342,
      "duration": 6.709000000000742
    },
    {
      "start": 7085.342,
      "duration": 4.834000000000742
    },
    {
      "start": 7090.468,
      "duration": 3.7489999999997963
    },
    {
      "start": 7095.217,
      "duration": 3.459000000000742
    },
    {
      "start": 7098.843,
      "duration": 7.416000000000167
    },
    {
      "start": 7107.217,
      "duration": 7.167000000000371
    },
    {
      "start": 7122.384,
      "duration": 5.792000000000371
    },
    {
      "start": 7128.301,
      "duration": 2.4589999999998327
    },
    {
      "start": 7142.634,
      "duration": 6.292000000000371
    },
    {
      "start": 7152.051,
      "duration": 2.8339999999998327
    },
    {
      "start": 7175.676,
      "duration": 2.3339999999998327
    },
    {
      "start": 7185.134,
      "duration": 3.792000000000371
    },
    {
      "start": 7219.342,
      "duration": 2.334000000000742
    },
    {
      "start": 7223.342,
      "duration": 4.834000000000742
    },
    {
      "start": 7229.01,
      "duration": 2.9160000000001673
    },
    {
      "start": 7234.885,
      "duration": 9.291000000000167
    },
    {
      "start": 7245.384,
      "duration": 5.501000000000204
    },
    {
      "start": 7251.551,
      "duration": 2.3339999999998327
    },
    {
      "start": 7255.342,
      "duration": 4.084000000000742
    },
    {
      "start": 7260.176,
      "duration": 2.7089999999998327
    },
    {
      "start": 7265.176,
      "duration": 2.7089999999998327
    },
    {
      "start": 7271.509,
      "duration": 4.542000000000371
    },
    {
      "start": 7276.384,
      "duration": 2.6260000000002037
    },
    {
      "start": 7279.676,
      "duration": 6.707999999999629
    },
    {
      "start": 7292.551,
      "duration": 5.125
    },
    {
      "start": 7298.301,
      "duration": 6.625
    },
    {
      "start": 7305.676,
      "duration": 9.25
    },
    {
      "start": 7315.634,
      "duration": 4.042000000000371
    },
    {
      "start": 7320.509,
      "duration": 3.2089999999998327
    },
    {
      "start": 7327.051,
      "duration": 3.165999999999258
    },
    {
      "start": 7332.885,
      "duration": 9.291000000000167
    },
    {
      "start": 7342.718,
      "duration": 3.6239999999997963
    },
    {
      "start": 7346.843,
      "duration": 4.0
    },
    {
      "start": 7351.384,
      "duration": 5.792000000000371
    },
    {
      "start": 7358.676,
      "duration": 4.041999999999462
    },
    {
      "start": 7363.217,
      "duration": 9.626000000000204
    },
    {
      "start": 7373.176,
      "duration": 3.165999999999258
    },
    {
      "start": 7377.176,
      "duration": 7.207999999999629
    },
    {
      "start": 7384.718,
      "duration": 15.623999999999796
    },
    {
      "start": 7401.509,
      "duration": 2.3760000000002037
    },
    {
      "start": 7404.384,
      "duration": 4.792000000000371
    },
    {
      "start": 7413.176,
      "duration": 3.6669999999994616
    },
    {
      "start": 7417.01,
      "duration": 3.832999999999629
    },
    {
      "start": 7421.01,
      "duration": 4.541000000000167
    },
    {
      "start": 7425.676,
      "duration": 6.0
    },
    {
      "start": 7432.676,
      "duration": 2.5
    },
    {
      "start": 7438.342,
      "duration": 3.084000000000742
    },
    {
      "start": 7445.676,
      "duration": 2.9169999999994616
    },
    {
      "start": 7451.176,
      "duration": 3.165999999999258
    },
    {
      "start": 7455.468,
      "duration": 7.041000000000167
    },
    {
      "start": 7462.676,
      "duration": 7.540999999999258
    },
    {
      "start": 7471.801,
      "duration": 5.375
    },
    {
      "start": 7479.01,
      "duration": 4.041000000000167
    },
    {
      "start": 7488.051,
      "duration": 4.5
    },
    {
      "start": 7492.801,
      "duration": 2.7919999999994616
    },
    {
      "start": 7496.384,
      "duration": 4.501000000000204
    },
    {
      "start": 7501.342,
      "duration": 11.209000000000742
    },
    {
      "start": 7513.509,
      "duration": 5.875
    },
    {
      "start": 7520.509,
      "duration": 4.832999999999629
    },
    {
      "start": 7525.384,
      "duration": 6.167000000000371
    },
    {
      "start": 7533.342,
      "duration": 4.668000000000575
    },
    {
      "start": 7541.843,
      "duration": 5.167000000000371
    },
    {
      "start": 7551.301,
      "duration": 4.375
    },
    {
      "start": 7556.676,
      "duration": 10.582999999999629
    },
    {
      "start": 7568.843,
      "duration": 28.16700000000037
    },
    {
      "start": 7599.134,
      "duration": 2.792000000000371
    },
    {
      "start": 7604.176,
      "duration": 3.332999999999629
    },
    {
      "start": 7607.634,
      "duration": 5.083999999999833
    },
    {
      "start": 7613.342,
      "duration": 3.0
    },
    {
      "start": 7616.843,
      "duration": 21.0
    },
    {
      "start": 7638.509,
      "duration": 5.0
    },
    {
      "start": 7643.634,
      "duration": 8.582999999999629
    },
    {
      "start": 7652.551,
      "duration": 3.665999999999258
    },
    {
      "start": 7656.342,
      "duration": 3.5010000000002037
    },
    {
      "start": 7661.217,
      "duration": 6.209000000000742
    },
    {
      "start": 7668.801,
      "duration": 7.707999999999629
    },
    {
      "start": 7677.468,
      "duration": 15.375
    },
    {
      "start": 7693.885,
      "duration": 7.125
    },
    {
      "start": 7701.217,
      "duration": 3.543000000000575
    },
    {
      "start": 7705.718,
      "duration": 10.458000000000538
    },
    {
      "start": 7718.176,
      "duration": 9.0
    },
    {
      "start": 7727.384,
      "duration": 4.626000000000204
    },
    {
      "start": 7733.676,
      "duration": 6.665999999999258
    },
    {
      "start": 7741.301,
      "duration": 2.875
    },
    {
      "start": 7744.342,
      "duration": 3.709000000000742
    },
    {
      "start": 7748.176,
      "duration": 4.25
    },
    {
      "start": 7753.01,
      "duration": 7.081999999999425
    },
    {
      "start": 7760.718,
      "duration": 5.042000000000371
    },
    {
      "start": 7766.051,
      "duration": 4.040999999999258
    },
    {
      "start": 7770.176,
      "duration": 3.7089999999998327
    },
    {
      "start": 7774.718,
      "duration": 8.208000000000538
    },
    {
      "start": 7785.01,
      "duration": 6.832999999999629
    },
    {
      "start": 7792.384,
      "duration": 8.501000000000204
    },
    {
      "start": 7802.342,
      "duration": 3.167000000000371
    },
    {
      "start": 7806.01,
      "duration": 3.6660000000001673
    },
    {
      "start": 7810.843,
      "duration": 3.8330000000005384
    },
    {
      "start": 7815.384,
      "duration": 3.125
    },
    {
      "start": 7819.176,
      "duration": 3.165999999999258
    },
    {
      "start": 7823.551,
      "duration": 3.125
    },
    {
      "start": 7831.676,
      "duration": 3.2919999999994616
    },
    {
      "start": 7835.342,
      "duration": 6.543000000000575
    },
    {
      "start": 7843.384,
      "duration": 3.4589999999998327
    },
    {
      "start": 7847.01,
      "duration": 4.0
    },
    {
      "start": 7851.051,
      "duration": 4.833999999999833
    },
    {
      "start": 7857.718,
      "duration": 2.4989999999997963
    },
    {
      "start": 7864.217,
      "duration": 6.167000000000371
    },
    {
      "start": 7871.01,
      "duration": 10.832999999999629
    },
    {
      "start": 7882.134,
      "duration": 4.417000000000371
    },
    {
      "start": 7887.176,
      "duration": 5.666999999999462
    },
    {
      "start": 7894.843,
      "duration": 4.333000000000538
    },
    {
      "start": 7899.634,
      "duration": 3.3760000000002037
    },
    {
      "start": 7904.551,
      "duration": 6.790999999999258
    },
    {
      "start": 7912.176,
      "duration": 8.5
    },
    {
      "start": 7921.134,
      "duration": 4.042000000000371
    },
    {
      "start": 7926.509,
      "duration": 3.417000000000371
    },
    {
      "start": 7930.051,
      "duration": 4.290999999999258
    },
    {
      "start": 7937.342,
      "duration": 3.543000000000575
    },
    {
      "start": 7942.176,
      "duration": 3.207999999999629
    },
    {
      "start": 7947.01,
      "duration": 3.3739999999997963
    },
    {
      "start": 7952.676,
      "duration": 2.832999999999629
    },
    {
      "start": 8018.76,
      "duration": 2.25
    },
    {
      "start": 8054.676,
      "duration": 3.582999999999629
    },
    {
      "start": 8064.134,
      "duration": 7.957999999999629
    },
    {
      "start": 8073.676,
      "duration": 5.875
    },
    {
      "start": 8079.676,
      "duration": 3.832999999999629
    },
    {
      "start": 8098.843,
      "duration": 4.042000000000371
    },
    {
      "start": 8173.342,
      "duration": 13.042000000000371
    },
    {
      "start": 8186.676,
      "duration": 2.665999999999258
    },
    {
      "start": 8189.843,
      "duration": 4.582999999999629
    },
    {
      "start": 8203.01,
      "duration": 21.0
    },
    {
      "start": 8239.051,
      "duration": 3.7920000000012806
    },
    {
      "start": 8247.676,
      "duration": 4.375
    },
    {
      "start": 8253.509,
      "duration": 5.416999999999462
    },
    {
      "start": 8260.843,
      "duration": 3.0
    },
    {
      "start": 8267.885,
      "duration": 4.457000000000335
    },
    {
      "start": 8274.051,
      "duration": 2.959000000000742
    },
    {
      "start": 8278.134,
      "duration": 12.416999999999462
    },
    {
      "start": 8292.01,
      "duration": 3.3320000000003347
    },
    {
      "start": 8295.509,
      "duration": 4.541999999999462
    },
    {
      "start": 8300.885,
      "duration": 4.875
    },
    {
      "start": 8306.384,
      "duration": 4.833000000000538
    },
    {
      "start": 8311.718,
      "duration": 5.875
    },
    {
      "start": 8377.551,
      "duration": 5.791000000001077
    },
    {
      "start": 8399.342,
      "duration": 7.417999999999665
    },
    {
      "start": 8410.634,
      "duration": 9.416999999999462
    },
    {
      "start": 8421.342,
      "duration": 11.417999999999665
    },
    {
      "start": 8433.342,
      "duration": 5.667999999999665
    },
    {
      "start": 8443.134,
      "duration": 2.6260000000002037
    },
    {
      "start": 8446.217,
      "duration": 10.708999999998923
    },
    {
      "start": 8457.342,
      "duration": 3.1669999999994616
    },
    {
      "start": 8465.01,
      "duration": 2.8330000000005384
    },
    {
      "start": 8468.676,
      "duration": 4.416000000001077
    },
    {
      "start": 8473.134,
      "duration": 2.7919999999994616
    },
    {
      "start": 8487.342,
      "duration": 7.667999999999665
    },
    {
      "start": 8495.134,
      "duration": 4.916999999999462
    },
    {
      "start": 8516.968,
      "duration": 3.7079999999987194
    },
    {
      "start": 8521.676,
      "duration": 2.5
    },
    {
      "start": 8533.509,
      "duration": 4.75
    },
    {
      "start": 8552.509,
      "duration": 2.875
    },
    {
      "start": 8559.384,
      "duration": 2.9580000000005384
    },
    {
      "start": 8562.676,
      "duration": 2.7080000000005384
    },
    {
      "start": 8567.384,
      "duration": 2.9580000000005384
    },
    {
      "start": 8572.801,
      "duration": 2.7080000000005384
    },
    {
      "start": 8575.843,
      "duration": 2.3329999999987194
    },
    {
      "start": 8635.76,
      "duration": 2.8739999999997963
    },
    {
      "start": 8639.301,
      "duration": 4.292000000001281
    },
    {
      "start": 8644.176,
      "duration": 2.6670000000012806
    },
    {
      "start": 8648.634,
      "duration": 5.084000000000742
    },
    {
      "start": 8656.176,
      "duration": 4.208000000000538
    },
    {
      "start": 8747.01,
      "duration": 8.0
    },
    {
      "start": 8811.217,
      "duration": 2.6260000000002037
    },
    {
      "start": 8817.01,
      "duration": 4.540999999999258
    },
    {
      "start": 8822.468,
      "duration": 3.5829999999987194
    },
    {
      "start": 8826.676,
      "duration": 4.833000000000538
    },
    {
      "start": 8831.843,
      "duration": 8.665999999999258
    },
    {
      "start": 8841.509,
      "duration": 4.166999999999462
    },
    {
      "start": 8847.176,
      "duration": 2.5420000000012806
    },
    {
      "start": 8852.968,
      "duration": 3.2079999999987194
    },
    {
      "start": 8858.01,
      "duration": 3.3320000000003347
    },
    {
      "start": 8861.968,
      "duration": 2.9169999999994616
    },
    {
      "start": 8869.509,
      "duration": 4.875
    },
    {
      "start": 8876.01,
      "duration": 3.4989999999997963
    },
    {
      "start": 8879.634,
      "duration": 7.708000000000538
    },
    {
      "start": 8888.342,
      "duration": 5.0
    },
    {
      "start": 8893.843,
      "duration": 5.832999999998719
    },
    {
      "start": 8901.176,
      "duration": 4.083000000000538
    },
    {
      "start": 8906.676,
      "duration": 4.25
    },
    {
      "start": 8911.509,
      "duration": 12.084000000000742
    },
    {
      "start": 8927.051,
      "duration": 4.959000000000742
    },
    {
      "start": 8932.301,
      "duration": 8.083000000000538
    },
    {
      "start": 8947.468,
      "duration": 3.5419999999994616
    },
    {
      "start": 8952.301,
      "duration": 3.2080000000005384
    },
    {
      "start": 8957.384,
      "duration": 2.6260000000002037
    },
    {
      "start": 8960.968,
      "duration": 3.0419999999994616
    },
    {
      "start": 8969.301,
      "duration": 2.4170000000012806
    },
    {
      "start": 8974.885,
      "duration": 3.0
    },
    {
      "start": 8978.676,
      "duration": 2.75
    },
    {
      "start": 8984.342,
      "duration": 2.208999999998923
    },
    {
      "start": 9056.843,
      "duration": 12.83299999999872
    },
    {
      "start": 9069.843,
      "duration": 17.415999999999258
    },
    {
      "start": 9115.676,
      "duration": 2.375
    },
    {
      "start": 9164.926,
      "duration": 5.75
    },
    {
      "start": 9265.342,
      "duration": 5.542999999999665
    },
    {
      "start": 9273.301,
      "duration": 2.875
    },
    {
      "start": 9278.301,
      "duration": 2.709000000000742
    },
    {
      "start": 9334.342,
      "duration": 2.5429999999996653
    },
    {
      "start": 9370.843,
      "duration": 2.2489999999997963
    },
    {
      "start": 9373.634,
      "duration": 3.5419999999994616
    },
    {
      "start": 9379.051,
      "duration": 8.291000000001077
    },
    {
      "start": 9387.676,
      "duration": 6.5
    },
    {
      "start": 9398.176,
      "duration": 7.25
    },
    {
      "start": 9407.509,
      "duration": 8.334000000000742
    },
    {
      "start": 9416.634,
      "duration": 3.2919999999994616
    },
    {
      "start": 9420.01,
      "duration": 4.082000000000335
    },
    {
      "start": 9428.801,
      "duration": 3.416000000001077
    },
    {
      "start": 9433.509,
      "duration": 3.7080000000005384
    },
    {
      "start": 9438.468,
      "duration": 3.9579999999987194
    },
    {
      "start": 9443.301,
      "duration": 5.875
    },
    {
      "start": 9450.301,
      "duration": 5.208000000000538
    },
    {
      "start": 9475.134,
      "duration": 3.8760000000002037
    },
    {
      "start": 9479.051,
      "duration": 3.5
    },
    {
      "start": 9484.176,
      "duration": 2.75
    },
    {
      "start": 9488.342,
      "duration": 3.208999999998923
    },
    {
      "start": 9519.676,
      "duration": 4.167000000001281
    },
    {
      "start": 9524.843,
      "duration": 6.0
    },
    {
      "start": 9533.342,
      "duration": 4.376000000000204
    },
    {
      "start": 9538.384,
      "duration": 3.7919999999994616
    },
    {
      "start": 9544.718,
      "duration": 3.4989999999997963
    },
    {
      "start": 9548.843,
      "duration": 4.498999999999796
    },
    {
      "start": 9563.384,
      "duration": 3.0419999999994616
    },
    {
      "start": 9567.676,
      "duration": 3.1670000000012806
    },
    {
      "start": 9571.01,
      "duration": 4.082000000000335
    },
    {
      "start": 9576.718,
      "duration": 2.25
    },
    {
      "start": 9581.176,
      "duration": 3.041000000001077
    },
    {
      "start": 9602.342,
      "duration": 2.5010000000002037
    },
    {
      "start": 9617.843,
      "duration": 4.75
    },
    {
      "start": 9624.217,
      "duration": 8.208999999998923
    },
    {
      "start": 9634.176,
      "duration": 3.709000000000742
    },
    {
      "start": 9638.342,
      "duration": 4.667999999999665
    },
    {
      "start": 9644.342,
      "duration": 3.5010000000002037
    },
    {
      "start": 9648.01,
      "duration": 3.75
    },
    {
      "start": 9652.634,
      "duration": 5.376000000000204
    },
    {
      "start": 9659.843,
      "duration": 2.75
    },
    {
      "start": 9669.176,
      "duration": 2.3330000000005384
    },
    {
      "start": 9682.384,
      "duration": 2.5010000000002037
    },
    {
      "start": 9686.718,
      "duration": 3.125
    },
    {
      "start": 9691.676,
      "duration": 3.1670000000012806
    },
    {
      "start": 9696.176,
      "duration": 3.2080000000005384
    },
    {
      "start": 9699.718,
      "duration": 2.9579999999987194
    },
    {
      "start": 9703.718,
      "duration": 2.4989999999997963
    },
    {
      "start": 9706.384,
      "duration": 2.5010000000002037
    },
    {
      "start": 9709.384,
      "duration": 3.334000000000742
    },
    {
      "start": 9714.342,
      "duration": 3.3760000000002037
    },
    {
      "start": 9724.384,
      "duration": 3.334000000000742
    },
    {
      "start": 9729.384,
      "duration": 2.5010000000002037
    },
    {
      "start": 9733.885,
      "duration": 2.6239999999997963
    },
    {
      "start": 9744.217,
      "duration": 2.708999999998923
    },
    {
      "start": 9749.342,
      "duration": 2.833999999998923
    },
    {
      "start": 9753.01,
      "duration": 2.4989999999997963
    },
    {
      "start": 9755.634,
      "duration": 3.2510000000002037
    },
    {
      "start": 9759.676,
      "duration": 2.416000000001077
    },
    {
      "start": 9763.968,
      "duration": 3.290999999999258
    },
    {
      "start": 9768.676,
      "duration": 3.209000000000742
    },
    {
      "start": 9777.301,
      "duration": 2.459000000000742
    },
    {
      "start": 9780.718,
      "duration": 2.4579999999987194
    },
    {
      "start": 9784.301,
      "duration": 3.041000000001077
    },
    {
      "start": 9792.676,
      "duration": 2.666000000001077
    },
    {
      "start": 9798.01,
      "duration": 2.5830000000005384
    },
    {
      "start": 9803.01,
      "duration": 2.7080000000005384
    },
    {
      "start": 9806.509,
      "duration": 2.5830000000005384
    },
    {
      "start": 9834.551,
      "duration": 6.125
    },
    {
      "start": 9841.342,
      "duration": 2.6679999999996653
    },
    {
      "start": 9845.217,
      "duration": 2.6679999999996653
    },
    {
      "start": 9852.968,
      "duration": 2.540999999999258
    },
    {
      "start": 9855.718,
      "duration": 3.125
    },
    {
      "start": 9869.384,
      "duration": 2.6260000000002037
    },
    {
      "start": 9885.176,
      "duration": 2.3330000000005384
    },
    {
      "start": 9891.134,
      "duration": 2.5419999999994616
    },
    {
      "start": 9895.801,
      "duration": 2.375
    },
    {
      "start": 9939.509,
      "duration": 66.45900000000074
    },
    {
      "start": 10078.342,
      "duration": 2.333999999998923
    },
    {
      "start": 10090.843,
      "duration": 2.875
    },
    {
      "start": 10096.885,
      "duration": 3.790999999999258
    },
    {
      "start": 10104.092,
      "duration": 7.458999999998923
    },
    {
      "start": 10137.885,
      "duration": 4.708000000000538
    },
    {
      "start": 10147.718,
      "duration": 9.0
    },
    {
      "start": 10157.926,
      "duration": 28.75
    },
    {
      "start": 10187.551,
      "duration": 9.875
    },
    {
      "start": 10200.718,
      "duration": 10.125
    },
    {
      "start": 10212.259,
      "duration": 19.04199999999946
    },
    {
      "start": 10231.76,
      "duration": 14.457000000000335
    },
    {
      "start": 10250.551,
      "duration": 16.91700000000128
    },
    {
      "start": 10268.259,
      "duration": 16.54199999999946
    },
    {
      "start": 10287.76,
      "duration": 7.582000000000335
    },
    {
      "start": 10298.259,
      "duration": 15.375
    },
    {
      "start": 10315.468,
      "duration": 6.873999999999796
    },
    {
      "start": 10404.926,
      "duration": 4.542000000001281
    },
    {
      "start": 10411.801,
      "duration": 3.291000000001077
    }
  ]
}
